marcus_main/__init__.py
marcus_main/marcus_main.py
marcus_main-0.1.1.dist-info/METADATA
marcus_main-0.1.1.dist-info/WHEEL
marcus_main-0.1.1.dist-info/top_level.txt
marcus_main-0.1.1.dist-info/RECORD
