Metadata-Version: 2.1
Name: marcus-main
Version: 0.1.1
Summary: An assignment that refactors the main function from Max's code into its own library
Home-page: 
Author: Marcus Rapacioli
Author-email: 
License: MIT
Classifier: Intended Audience :: Developers
Classifier: License :: OSI Approved :: MIT License
Classifier: Programming Language :: Python
Classifier: Programming Language :: Python :: 3
Classifier: Programming Language :: Python :: 3.6
Classifier: Programming Language :: Python :: 3.7
Classifier: Programming Language :: Python :: 3.8
Classifier: Programming Language :: Python :: 3.9
Classifier: Operating System :: OS Independent
Requires-Dist: sqlalchemy
Requires-Dist: polygon
